{
	"class" : {
		 },
	"instance" : {
		"aClassAdded:" : "ThierryGoubier 11/27/2014 23:13:21",
		"aClassCommented:" : "ThierryGoubier 11/27/2014 23:13:21",
		"aClassModifiedClassDefinition:" : "ThierryGoubier 11/27/2014 23:13:21",
		"aClassRecategorized:" : "ThierryGoubier 11/27/2014 23:13:21",
		"aClassRemoved:" : "ThierryGoubier 11/27/2014 23:13:21",
		"aClassRenamed:" : "ThierryGoubier 12/4/2014 17:29:06",
		"aClassReorganized:" : "ThierryGoubier 11/27/2014 23:13:21",
		"aClassRepackaged:" : "ThierryGoubier 11/27/2014 23:13:21",
		"aMethodAdded:" : "ThierryGoubier 11/27/2014 23:13:21",
		"aMethodRecategorized:" : "ThierryGoubier 11/27/2014 23:13:21",
		"aMethodRemoved:" : "ThierryGoubier 11/27/2014 23:13:21",
		"accept:notifying:" : "ThierryGoubier 11/27/2014 23:13:21",
		"asString" : "ThierryGoubier 11/27/2014 23:13:21",
		"buildTextMenu:on:with:" : "ThierryGoubier 11/27/2014 23:13:21",
		"classSearchCommands" : "ThierryGoubier 11/27/2014 23:13:21",
		"contents" : "ThierryGoubier 11/27/2014 23:13:21",
		"doubleClickOn:in:" : "ThierryGoubier 12/13/2014 18:42",
		"findAllClass:" : "ThierryGoubier 11/27/2014 23:13:21",
		"findClass:" : "ThierryGoubier 11/27/2014 23:13:21",
		"findMethod:in:" : "ThierryGoubier 11/27/2014 23:13:21",
		"indent" : "ThierryGoubier 11/27/2014 23:13:21",
		"isClassNode" : "ThierryGoubier 11/27/2014 23:13:21",
		"isInRBEnvironment:" : "ThierryGoubier 11/27/2014 23:13:21",
		"isStyled" : "ThierryGoubier 11/27/2014 23:13:21",
		"itemClass" : "ThierryGoubier 11/27/2014 23:13:21",
		"itemOrganization" : "ThierryGoubier 11/27/2014 23:13:21",
		"navigationCommands" : "ThierryGoubier 11/27/2014 23:13:21",
		"orgBeginning" : "ThierryGoubier 11/27/2014 23:13:21",
		"orgEnding" : "ThierryGoubier 11/27/2014 23:13:21",
		"orgExtension" : "ThierryGoubier 11/27/2014 23:13:21",
		"parseAcceptText:notifying:" : "ThierryGoubier 11/27/2014 23:13:21",
		"privateClass" : "ThierryGoubier 11/27/2014 23:13:21",
		"refactoringCommands" : "ThierryGoubier 11/27/2014 23:13:21",
		"removeClassCommand" : "ThierryGoubier 11/27/2014 23:13:21",
		"rewriteStringOfVars:into:" : "ThierryGoubier 11/27/2014 23:13:21",
		"sourceClass" : "ThierryGoubier 11/27/2014 23:13:21",
		"sourceCode" : "ThierryGoubier 11/27/2014 23:13:21",
		"sourceComment" : "ThierryGoubier 12/4/2014 17:29:06",
		"styleClass" : "ThierryGoubier 11/27/2014 23:13:21",
		"subclasses" : "ThierryGoubier 11/27/2014 23:13:21",
		"superclass" : "ThierryGoubier 11/27/2014 23:13:21",
		"title" : "ThierryGoubier 11/27/2014 23:13:21" } }
