{
	"class" : {
		"on:for:" : "ThierryGoubier 1/15/2014 17:47:37" },
	"instance" : {
		"addItemToMenu:" : "ThierryGoubier 1/15/2014 17:47:37",
		"buildShortcut:" : "ThierryGoubier 1/15/2014 17:47:37",
		"execute" : "ThierryGoubier 1/15/2014 17:47:37",
		"icon" : "ThierryGoubier 1/15/2014 17:47:37",
		"isActive" : "ThierryGoubier 1/15/2014 17:47:37",
		"isEnabled" : "ThierryGoubier 1/15/2014 17:47:37",
		"keyString" : "ThierryGoubier 1/15/2014 17:47:37",
		"keystroke" : "ThierryGoubier 1/15/2014 17:47:37",
		"label" : "ThierryGoubier 1/15/2014 17:47:37",
		"on:for:" : "ThierryGoubier 1/15/2014 17:47:37",
		"perform:orSendTo:" : "ThierryGoubier 1/15/2014 17:47:37",
		"select:with:" : "ThierryGoubier 1/15/2014 17:47:37",
		"setTarget:requestor:" : "ThierryGoubier 1/15/2014 17:47:37",
		"wantsButton" : "ThierryGoubier 1/15/2014 17:47:37",
		"wantsKeyboard" : "ThierryGoubier 1/15/2014 17:47:37",
		"wantsMenu" : "ThierryGoubier 1/15/2014 17:47:37" } }
