{
	"class" : {
		"on:for:" : "ThierryGoubier 2/27/2014 17:17:20" },
	"instance" : {
		"addItemToMenu:" : "ThierryGoubier 2/27/2014 17:17:20",
		"buildShortcut:" : "ThierryGoubier 2/27/2014 17:17:20",
		"execute" : "ThierryGoubier 2/27/2014 17:17:20",
		"icon" : "ThierryGoubier 2/27/2014 17:17:20",
		"isActive" : "ThierryGoubier 2/27/2014 17:17:20",
		"isEnabled" : "ThierryGoubier 2/27/2014 17:17:20",
		"keyString" : "ThierryGoubier 3/3/2014 12:54",
		"keystroke" : "ThierryGoubier 2/27/2014 17:17:20",
		"label" : "ThierryGoubier 2/27/2014 17:17:20",
		"on:for:" : "ThierryGoubier 2/27/2014 17:17:20",
		"setTarget:requestor:" : "ThierryGoubier 2/27/2014 17:17:20",
		"wantsKeyboard" : "ThierryGoubier 2/27/2014 17:17:20",
		"wantsMenu" : "ThierryGoubier 2/27/2014 17:17:20" } }
