{
	"class" : {
		"with:parent:" : "ThierryGoubier 7/5/2014 19:16:36" },
	"instance" : {
		"aCategoryAdded:" : "ThierryGoubier 7/5/2014 19:16:36",
		"aCategoryRemoved:" : "ThierryGoubier 7/5/2014 19:16:36",
		"aCategoryRenamed:" : "ThierryGoubier 7/5/2014 19:16:36",
		"aClassAdded:" : "ThierryGoubier 7/5/2014 19:16:36",
		"aClassCommented:" : "ThierryGoubier 7/5/2014 19:16:36",
		"aClassRecategorized:" : "ThierryGoubier 7/5/2014 19:16:36",
		"aClassRemoved:" : "ThierryGoubier 7/5/2014 19:16:36",
		"aClassRenamed:" : "ThierryGoubier 7/5/2014 19:16:36",
		"aClassReorganized:" : "ThierryGoubier 7/5/2014 19:16:36",
		"aClassRepackaged:" : "ThierryGoubier 7/5/2014 19:16:36",
		"aMCWorkingCopyCreated:" : "ThierryGoubier 7/5/2014 19:16:36",
		"aMCWorkingCopyDeleted:" : "ThierryGoubier 7/5/2014 19:16:36",
		"aMCWorkingCopyModified:" : "ThierryGoubier 7/5/2014 19:16:36",
		"aMethodAdded:" : "ThierryGoubier 7/5/2014 19:16:36",
		"aMethodRecategorized:" : "ThierryGoubier 7/5/2014 19:16:36",
		"aMethodRemoved:" : "ThierryGoubier 7/5/2014 19:16:36",
		"aRPackageCreated:" : "ThierryGoubier 7/5/2014 19:16:36",
		"aRPackageUnregistered:" : "ThierryGoubier 7/5/2014 19:16:36",
		"accept:notifying:" : "ThierryGoubier 7/5/2014 19:16:36",
		"acceptDropItem:" : "ThierryGoubier 7/5/2014 19:16:36",
		"asCategories" : "ThierryGoubier 7/5/2014 19:16:36",
		"asPerRBEnvironment:" : "ThierryGoubier 7/5/2014 19:16:36",
		"asString" : "ThierryGoubier 7/5/2014 19:16:36",
		"asStringIn:" : "ThierryGoubier 7/5/2014 19:16:36",
		"contents" : "ThierryGoubier 7/5/2014 19:16:36",
		"doubleClickOn:in:" : "ThierryGoubier 7/5/2014 19:16:36",
		"dropItem:" : "ThierryGoubier 7/5/2014 19:16:36",
		"findKeywordsCategory:" : "ThierryGoubier 7/5/2014 19:16:36",
		"findMethod:in:" : "ThierryGoubier 7/5/2014 19:16:36",
		"findPackage:" : "ThierryGoubier 7/5/2014 19:16:36",
		"findPackageCategory:" : "ThierryGoubier 7/5/2014 19:16:36",
		"icon" : "ThierryGoubier 7/5/2014 19:16:36",
		"isInRBEnvironment:" : "ThierryGoubier 7/5/2014 19:16:36",
		"isPackageNode" : "ThierryGoubier 7/5/2014 19:16:36",
		"isStyled" : "ThierryGoubier 7/5/2014 19:16:36",
		"mcWorkingCopy" : "ThierryGoubier 7/5/2014 19:16:36",
		"packageName" : "ThierryGoubier 7/5/2014 19:16:36",
		"rpackage" : "ThierryGoubier 7/5/2014 19:16:36",
		"rpackageCommands" : "ThierryGoubier 7/5/2014 19:16:36",
		"sourceCode" : "ThierryGoubier 7/5/2014 19:16:36",
		"title" : "ThierryGoubier 7/5/2014 19:16:36" } }
