{
	"class" : {
		"aCategoryAdded:" : "ThierryGoubier 8/28/2014 19:10:58",
		"aCategoryRemoved:" : "ThierryGoubier 8/28/2014 19:10:58",
		"aCategoryRenamed:" : "ThierryGoubier 8/28/2014 19:10:58",
		"aClassAdded:" : "ThierryGoubier 8/28/2014 19:10:58",
		"aClassCommented:" : "ThierryGoubier 8/28/2014 19:10:58",
		"aClassRecategorized:" : "ThierryGoubier 8/28/2014 19:10:58",
		"aClassRemoved:" : "ThierryGoubier 8/28/2014 19:10:58",
		"aClassRenamed:" : "ThierryGoubier 8/28/2014 19:10:58",
		"aClassReorganized:" : "ThierryGoubier 8/28/2014 19:10:58",
		"aClassRepackaged:" : "ThierryGoubier 8/28/2014 19:10:58",
		"aMCWorkingCopyCreated:" : "ThierryGoubier 8/28/2014 19:10:58",
		"aMCWorkingCopyDeleted:" : "ThierryGoubier 8/28/2014 19:10:58",
		"aMCWorkingCopyModified:" : "ThierryGoubier 8/28/2014 19:10:58",
		"aMethodAdded:" : "ThierryGoubier 8/28/2014 19:10:58",
		"aMethodRecategorized:" : "ThierryGoubier 8/28/2014 19:10:58",
		"aMethodRemoved:" : "ThierryGoubier 8/28/2014 19:10:58",
		"aNodeAdded:" : "ThierryGoubier 8/28/2014 19:10:58",
		"aNodeRemoved:" : "ThierryGoubier 8/28/2014 19:10:58",
		"aNodeToRebuilt:" : "ThierryGoubier 8/28/2014 19:10:58",
		"aNodeToUpdate:" : "ThierryGoubier 8/28/2014 19:10:58",
		"aRPackageCreated:" : "ThierryGoubier 8/28/2014 19:10:58",
		"aRPackageUnregistered:" : "ThierryGoubier 8/28/2014 19:10:58",
		"altBrowserSettingsOn:" : "ThierryGoubier 8/28/2014 19:10:58",
		"announcer" : "ThierryGoubier 8/28/2014 19:10:58",
		"asCategories" : "ThierryGoubier 8/28/2014 19:10:58",
		"categories" : "ThierryGoubier 8/28/2014 19:10:58",
		"categories:" : "ThierryGoubier 8/28/2014 19:10:58",
		"categoriesAsSetting" : "ThierryGoubier 8/28/2014 19:10:58",
		"categoriesAsSetting:" : "ThierryGoubier 8/28/2014 19:10:58",
		"debug" : "ThierryGoubier 8/28/2014 19:10:58",
		"debug:" : "ThierryGoubier 8/28/2014 19:10:58",
		"defaultBrowser" : "ThierryGoubier 8/28/2014 19:10:58",
		"defaultBrowser:" : "ThierryGoubier 8/28/2014 19:10:58",
		"defaultPackageCategoriesNames" : "ThierryGoubier 8/28/2014 19:10:58",
		"findPackage:" : "ThierryGoubier 8/28/2014 19:10:58",
		"findPackageCategory:" : "ThierryGoubier 8/28/2014 19:10:58",
		"fullHierarchyOnClass:" : "ThierryGoubier 8/28/2014 19:10:58",
		"fullHierarchyOnClass:in:" : "ThierryGoubier 8/28/2014 19:10:58",
		"fullHierarchyOnClass:selector:" : "ThierryGoubier 8/28/2014 19:10:58",
		"fullHierarchyOnClass:selector:in:" : "ThierryGoubier 8/28/2014 19:10:58",
		"fullOnClass:" : "ThierryGoubier 8/28/2014 19:10:58",
		"fullOnClass:in:" : "ThierryGoubier 8/28/2014 19:10:58",
		"fullOnClass:selector:" : "ThierryGoubier 8/28/2014 19:10:58",
		"fullOnClass:selector:highlight:" : "ThierryGoubier 8/28/2014 19:10:58",
		"fullOnEnvironment:" : "ThierryGoubier 8/28/2014 19:10:58",
		"fullOnMethods:" : "ThierryGoubier 8/28/2014 19:10:58",
		"fullOnPackage:in:" : "ThierryGoubier 8/28/2014 19:10:58",
		"getItemsFor:from:" : "ThierryGoubier 8/28/2014 19:10:58",
		"getRootItems" : "ThierryGoubier 8/28/2014 19:10:58",
		"initialize" : "ThierryGoubier 8/28/2014 19:10:58",
		"newOnClass:" : "ThierryGoubier 8/28/2014 19:10:58",
		"newOnClass:selector:" : "ThierryGoubier 8/28/2014 19:10:58",
		"open" : "ThierryGoubier 8/28/2014 19:10:58",
		"openMessageList:name:autoSelect:" : "ThierryGoubier 8/28/2014 19:10:58",
		"openMessageList:name:autoSelect:refreshingBlockSelector:" : "ThierryGoubier 8/28/2014 19:10:58",
		"recentPackages" : "ThierryGoubier 8/28/2014 19:10:58",
		"registerInAppRegistry" : "ThierryGoubier 8/28/2014 19:10:58",
		"registerOnSystemAnnouncements" : "ThierryGoubier 8/28/2014 19:10:58",
		"reset" : "ThierryGoubier 8/28/2014 19:10:58",
		"root" : "ThierryGoubier 8/28/2014 19:10:58",
		"rootItems" : "ThierryGoubier 8/28/2014 19:10:58",
		"taskbarIcon" : "ThierryGoubier 8/28/2014 19:10:58",
		"temporary" : "ThierryGoubier 8/28/2014 19:10:58",
		"temporary:" : "ThierryGoubier 8/28/2014 19:10:58",
		"updateCategories" : "ThierryGoubier 8/28/2014 19:10:58" },
	"instance" : {
		"aClassRedefined:" : "ThierryGoubier 8/28/2014 19:10:58",
		"aMethodUpdated:" : "ThierryGoubier 8/28/2014 19:10:58",
		"aNodeAdded:" : "ThierryGoubier 8/28/2014 19:10:58",
		"aNodeRebuilt:" : "ThierryGoubier 8/28/2014 19:10:58",
		"aNodeRemoved:" : "ThierryGoubier 8/28/2014 19:10:58",
		"aNodeUpdated:" : "ThierryGoubier 8/28/2014 19:10:58",
		"aRootsChanged" : "ThierryGoubier 8/28/2014 19:10:58",
		"acceptDroppingMorph:event:inMorph:" : "ThierryGoubier 8/28/2014 19:10:58",
		"addModelItemsToWindowMenu:" : "ThierryGoubier 8/28/2014 19:10:58",
		"browseFinderResults" : "ThierryGoubier 8/28/2014 19:10:58",
		"buildTextMenu:" : "ThierryGoubier 8/28/2014 19:10:58",
		"buildTreeMenu:" : "ThierryGoubier 8/28/2014 19:10:58",
		"canDiscardEdits" : "ThierryGoubier 8/28/2014 19:10:58",
		"close" : "ThierryGoubier 8/28/2014 19:10:58",
		"defaultCommands" : "ThierryGoubier 8/28/2014 19:10:58",
		"defaultTextMorph" : "ThierryGoubier 8/28/2014 19:10:58",
		"defaultTreeMorph" : "ThierryGoubier 8/28/2014 19:10:58",
		"delete" : "ThierryGoubier 8/28/2014 19:10:58",
		"doubleClick" : "ThierryGoubier 8/28/2014 19:10:58",
		"dragPassengerFor:inMorph:" : "ThierryGoubier 8/28/2014 19:10:58",
		"expandAllNodes" : "ThierryGoubier 8/28/2014 19:10:58",
		"findMorphNodeForAbstractItem:" : "ThierryGoubier 8/28/2014 19:10:58",
		"findMorphNodeForItem:" : "ThierryGoubier 8/28/2014 19:10:58",
		"finder" : "ThierryGoubier 8/28/2014 19:10:58",
		"hasFinder" : "ThierryGoubier 8/28/2014 19:10:58",
		"history" : "ThierryGoubier 8/28/2014 19:10:58",
		"isSelectionUpdate" : "ThierryGoubier 8/28/2014 19:10:58",
		"open" : "ThierryGoubier 8/28/2014 19:10:58",
		"rbEnvironment" : "ThierryGoubier 8/28/2014 19:10:58",
		"rbEnvironment:" : "ThierryGoubier 8/28/2014 19:10:58",
		"registerToAnnouncements" : "ThierryGoubier 8/28/2014 19:10:58",
		"release" : "ThierryGoubier 8/28/2014 19:10:58",
		"rootItems" : "ThierryGoubier 8/28/2014 19:10:58",
		"rootNodeClassFromItem:" : "ThierryGoubier 8/28/2014 19:10:58",
		"rootNodeFromItem:" : "ThierryGoubier 8/28/2014 19:10:58",
		"selectPathForAbstractItem:" : "ThierryGoubier 8/28/2014 19:10:58",
		"selectedItem" : "ThierryGoubier 8/28/2014 19:10:58",
		"selection:" : "ThierryGoubier 8/28/2014 19:10:58",
		"source" : "ThierryGoubier 8/28/2014 19:10:58",
		"spawnHierarchyForClass:selector:" : "ThierryGoubier 8/28/2014 19:10:58",
		"taskbarIcon" : "ThierryGoubier 8/28/2014 19:10:58",
		"textMorph" : "ThierryGoubier 8/28/2014 19:10:58",
		"title" : "ThierryGoubier 8/28/2014 19:10:58",
		"toggleFinder" : "ThierryGoubier 8/28/2014 19:10:58",
		"treeMorph" : "ThierryGoubier 8/28/2014 19:10:58",
		"updateTextKeymap" : "ThierryGoubier 8/28/2014 19:10:58",
		"updateTitle" : "ThierryGoubier 8/28/2014 19:10:58",
		"updateTreeKeymap" : "ThierryGoubier 8/28/2014 19:10:58",
		"wantsDroppedMorph:event:inMorph:" : "ThierryGoubier 8/28/2014 19:10:58",
		"withSelectionDo:" : "ThierryGoubier 8/28/2014 19:10:58" } }
