{
	"class" : {
		 },
	"instance" : {
		"docMCPackageOwnership" : "ThierryGoubier 10/3/2014 17:23:28",
		"setUp" : "ThierryGoubier 10/3/2014 17:23:28",
		"tearDown" : "ThierryGoubier 10/3/2014 17:23:28",
		"testAddRemoveSystemCategory" : "ThierryGoubier 10/3/2014 17:23:28",
		"testAddSystemCategory" : "ThierryGoubier 10/3/2014 17:23:28",
		"testChangeTestClassDefinition" : "ThierryGoubier 10/3/2014 17:23:28",
		"testHasPackage" : "ThierryGoubier 10/3/2014 17:23:28",
		"testRemoveAsYetUnclassifiedOnRecategorizeMethod" : "ThierryGoubier 10/3/2014 17:23:28",
		"testRemoveAsYetUnclassifiedOnRemoveMethod" : "ThierryGoubier 10/3/2014 17:23:28",
		"testRemoveProtocol" : "ThierryGoubier 10/3/2014 17:23:28",
		"testSearchMethod" : "ThierryGoubier 10/3/2014 17:23:28",
		"testSelectPackage" : "ThierryGoubier 10/3/2014 17:23:28",
		"testSelectTestClass" : "ThierryGoubier 10/3/2014 17:23:28" } }
