{
	"class" : {
		 },
	"instance" : {
		"docMCPackageOwnership" : "ThierryGoubier 5/12/2015 19:55:57",
		"setUp" : "ThierryGoubier 5/12/2015 19:55:57",
		"tearDown" : "ThierryGoubier 5/12/2015 19:55:57",
		"testAddRemoveSystemCategory" : "ThierryGoubier 5/12/2015 19:55:57",
		"testAddSystemCategory" : "ThierryGoubier 5/12/2015 19:55:57",
		"testChangeTestClassDefinition" : "ThierryGoubier 5/12/2015 19:55:57",
		"testHasPackage" : "ThierryGoubier 5/12/2015 19:55:57",
		"testRemoveAsYetUnclassifiedOnRecategorizeMethod" : "ThierryGoubier 5/12/2015 19:55:57",
		"testRemoveAsYetUnclassifiedOnRemoveMethod" : "ThierryGoubier 5/12/2015 19:55:57",
		"testRemoveProtocol" : "ThierryGoubier 5/12/2015 19:55:57",
		"testSearchMethod" : "ThierryGoubier 5/12/2015 19:55:57",
		"testSelectPackage" : "ThierryGoubier 5/12/2015 19:55:57",
		"testSelectTestClass" : "ThierryGoubier 5/12/2015 19:55:57" } }
