{
	"class" : {
		 },
	"instance" : {
		"accept:notifying:" : "ThierryGoubier 10/5/2014 09:30:29",
		"acceptDropItem:" : "ThierryGoubier 10/5/2014 09:30:29",
		"buildTextMenu:on:with:" : "ThierryGoubier 10/5/2014 09:30:29",
		"compiledMethod" : "ThierryGoubier 10/5/2014 09:30:29",
		"contents" : "ThierryGoubier 10/5/2014 09:30:29",
		"dropItem:" : "ThierryGoubier 10/5/2014 09:30:29",
		"findMethod:in:" : "ThierryGoubier 10/5/2014 09:30:29",
		"formatCommand" : "ThierryGoubier 10/5/2014 09:30:29",
		"icon" : "ThierryGoubier 10/5/2014 09:30:29",
		"isInRBEnvironment:" : "ThierryGoubier 10/5/2014 09:30:29",
		"isMethodNode" : "ThierryGoubier 10/5/2014 09:30:29",
		"isStyled" : "ThierryGoubier 10/5/2014 09:30:29",
		"methodCategory" : "ThierryGoubier 10/5/2014 09:30:29",
		"navigationCommands" : "ThierryGoubier 10/5/2014 09:30:29",
		"removeCommand" : "ThierryGoubier 10/5/2014 09:30:29",
		"runTestCommand" : "ThierryGoubier 10/5/2014 09:30:29",
		"selector" : "ThierryGoubier 10/5/2014 09:30:29",
		"sourceClass" : "ThierryGoubier 10/5/2014 09:30:29",
		"sourceCode" : "ThierryGoubier 10/5/2014 09:30:29",
		"title" : "ThierryGoubier 10/5/2014 09:30:29",
		"wDebugTreeCommands" : "ThierryGoubier 10/5/2014 09:30:29" } }
