{
	"class" : {
		 },
	"instance" : {
		"aCategoryAdded:" : "ThierryGoubier 8/30/2014 16:51:00",
		"aCategoryRemoved:" : "ThierryGoubier 8/30/2014 16:51:00",
		"aCategoryRenamed:" : "ThierryGoubier 8/30/2014 16:51:00",
		"aClassAdded:" : "ThierryGoubier 8/30/2014 16:51:00",
		"aClassCommented:" : "ThierryGoubier 8/30/2014 16:51:00",
		"aClassRecategorized:" : "ThierryGoubier 8/30/2014 16:51:00",
		"aClassRemoved:" : "ThierryGoubier 8/30/2014 16:51:00",
		"aClassRenamed:" : "ThierryGoubier 8/30/2014 16:51:00",
		"aClassReorganized:" : "ThierryGoubier 8/30/2014 16:51:00",
		"aClassRepackaged:" : "ThierryGoubier 8/30/2014 16:51:00",
		"aMCWorkingCopyCreated:" : "ThierryGoubier 8/30/2014 16:51:00",
		"aMCWorkingCopyDeleted:" : "ThierryGoubier 8/30/2014 16:51:00",
		"aMCWorkingCopyModified:" : "ThierryGoubier 8/30/2014 16:51:00",
		"aMethodAdded:" : "ThierryGoubier 8/30/2014 16:51:00",
		"aMethodRecategorized:" : "ThierryGoubier 8/30/2014 16:51:00",
		"aMethodRemoved:" : "ThierryGoubier 8/30/2014 16:51:00",
		"aRPackageCreated:" : "ThierryGoubier 8/30/2014 16:51:00",
		"aRPackageUnregistered:" : "ThierryGoubier 8/30/2014 16:51:00",
		"acceptDropItem:" : "ThierryGoubier 8/30/2014 16:51:00",
		"addRPackage:" : "ThierryGoubier 8/30/2014 16:51:00",
		"asCategories" : "ThierryGoubier 8/30/2014 16:51:00",
		"asPerRBEnvironment:" : "ThierryGoubier 8/30/2014 16:51:00",
		"asString" : "ThierryGoubier 8/30/2014 16:51:00",
		"categoryName" : "ThierryGoubier 8/30/2014 16:51:00",
		"contents" : "ThierryGoubier 8/30/2014 16:51:00",
		"dropItem:" : "ThierryGoubier 8/30/2014 16:51:00",
		"findKeywordsCategory:" : "ThierryGoubier 8/30/2014 16:51:00",
		"findMethod:in:" : "ThierryGoubier 8/30/2014 16:51:00",
		"findPackage:" : "ThierryGoubier 8/30/2014 16:51:00",
		"findPackageCategory:" : "ThierryGoubier 8/30/2014 16:51:00",
		"icon" : "ThierryGoubier 8/30/2014 16:51:00",
		"isInRBEnvironment:" : "ThierryGoubier 8/30/2014 16:51:00",
		"isPackageCategoryNode" : "ThierryGoubier 8/30/2014 16:51:00",
		"rcTreeCommands" : "ThierryGoubier 8/30/2014 16:51:00",
		"removeRPackage:" : "ThierryGoubier 8/30/2014 16:51:00",
		"sourceCode" : "ThierryGoubier 8/30/2014 16:51:00",
		"title" : "ThierryGoubier 8/30/2014 16:51:00",
		"trimmedCategoryName" : "ThierryGoubier 8/30/2014 16:51:00" } }
