{
	"class" : {
		 },
	"instance" : {
		"aCategoryAdded:" : "ThierryGoubier 2/14/2014 10:24:13",
		"aCategoryRemoved:" : "ThierryGoubier 2/14/2014 10:24:13",
		"aCategoryRenamed:" : "ThierryGoubier 2/14/2014 10:24:13",
		"aClassAdded:" : "ThierryGoubier 2/14/2014 10:24:13",
		"aClassCommented:" : "ThierryGoubier 2/14/2014 10:24:13",
		"aClassRecategorized:" : "ThierryGoubier 2/14/2014 10:24:13",
		"aClassRemoved:" : "ThierryGoubier 2/14/2014 10:24:13",
		"aClassRenamed:" : "ThierryGoubier 2/14/2014 10:24:13",
		"aClassReorganized:" : "ThierryGoubier 2/14/2014 10:24:13",
		"aClassRepackaged:" : "ThierryGoubier 2/14/2014 10:24:13",
		"aMCWorkingCopyCreated:" : "ThierryGoubier 2/24/2014 11:04",
		"aMCWorkingCopyDeleted:" : "ThierryGoubier 2/24/2014 11:16",
		"aMCWorkingCopyModified:" : "ThierryGoubier 2/14/2014 10:24:13",
		"aMethodAdded:" : "ThierryGoubier 2/14/2014 10:24:13",
		"aMethodRecategorized:" : "ThierryGoubier 2/14/2014 10:24:13",
		"aMethodRemoved:" : "ThierryGoubier 2/14/2014 10:24:13",
		"aRPackageCreated:" : "ThierryGoubier 2/14/2014 10:24:13",
		"aRPackageUnregistered:" : "ThierryGoubier 2/14/2014 10:24:13",
		"acceptDropItem:" : "ThierryGoubier 2/20/2014 13:08",
		"addChildItem:" : "ThierryGoubier 2/24/2014 10:58",
		"addRPackage:" : "ThierryGoubier 2/24/2014 11:10",
		"asPerRBEnvironment:" : "ThierryGoubier 2/14/2014 10:24:13",
		"asString" : "ThierryGoubier 2/14/2014 10:24:13",
		"childNodeClassFromItem:" : "ThierryGoubier 2/14/2014 10:24:13",
		"childrenItems" : "ThierryGoubier 2/14/2014 10:24:13",
		"dropItem:" : "ThierryGoubier 2/24/2014 11:22",
		"findMethod:in:" : "ThierryGoubier 2/14/2014 10:24:13",
		"findPackage:" : "ThierryGoubier 2/14/2014 10:24:13",
		"icon" : "ThierryGoubier 2/14/2014 10:24:13",
		"isInRBEnvironment:" : "ThierryGoubier 2/18/2014 14:22",
		"isPackageCategoryNode" : "ThierryGoubier 2/18/2014 12:47",
		"rcTreeCommands" : "ThierryGoubier 2/14/2014 10:24:13",
		"removeChildItem:" : "ThierryGoubier 2/17/2014 17:17",
		"removeRPackage:" : "ThierryGoubier 2/24/2014 11:16",
		"sourceCode" : "ThierryGoubier 2/14/2014 10:24:13",
		"title" : "ThierryGoubier 2/14/2014 10:24:13" } }
