{
	"class" : {
		 },
	"instance" : {
		"aClassCommented:" : "ThierryGoubier 12/14/2014 17:01:14",
		"aMethodAdded:" : "ThierryGoubier 12/14/2014 17:01:14",
		"aMethodRecategorized:" : "ThierryGoubier 12/14/2014 17:01:14",
		"aMethodRemoved:" : "ThierryGoubier 12/14/2014 17:01:14",
		"accept:notifying:" : "ThierryGoubier 12/14/2014 17:01:14",
		"acceptDropItem:" : "ThierryGoubier 12/14/2014 17:01:14",
		"contents" : "ThierryGoubier 12/14/2014 17:01:14",
		"dropItem:" : "ThierryGoubier 12/14/2014 17:01:14",
		"findMethod:in:" : "ThierryGoubier 12/14/2014 17:01:14",
		"findMethodCategory:in:" : "ThierryGoubier 12/14/2014 17:01:14",
		"formatCommand" : "ThierryGoubier 12/14/2014 17:01:14",
		"icon" : "ThierryGoubier 12/14/2014 17:01:14",
		"isInRBEnvironment:" : "ThierryGoubier 12/14/2014 17:01:14",
		"isMethodCategoryNode" : "ThierryGoubier 12/14/2014 17:01:14",
		"isStyled" : "ThierryGoubier 12/14/2014 17:01:14",
		"methodCategory" : "ThierryGoubier 12/14/2014 17:01:14",
		"privateClass" : "ThierryGoubier 12/14/2014 17:01:14",
		"sourceClass" : "ThierryGoubier 12/14/2014 17:01:14",
		"sourceCode" : "ThierryGoubier 12/14/2014 17:01:14",
		"sourceComment" : "ThierryGoubier 12/14/2014 17:01:14",
		"treeAreaCommands" : "ThierryGoubier 12/14/2014 17:01:14" } }
