{
	"class" : {
		 },
	"instance" : {
		"asString" : "ThierryGoubier 3/12/2014 17:21:00",
		"buildTextMenu:on:with:" : "ThierryGoubier 3/12/2014 17:21:00",
		"buildTreeMenu:on:with:" : "ThierryGoubier 3/12/2014 17:21:00",
		"childNodeFromItem:" : "ThierryGoubier 3/12/2014 17:21:00",
		"childrenItems" : "ThierryGoubier 3/12/2014 17:21:00",
		"contents" : "ThierryGoubier 3/12/2014 17:21:00",
		"doubleClickIn:" : "ThierryGoubier 3/12/2014 17:21:00",
		"findItem:" : "ThierryGoubier 3/12/2014 17:21:00",
		"icon" : "ThierryGoubier 3/12/2014 17:21:00",
		"isStyled" : "ThierryGoubier 3/12/2014 17:21:00",
		"rbEnvironment" : "ThierryGoubier 3/12/2014 17:21:00",
		"rbEnvironment:" : "ThierryGoubier 3/12/2014 17:21:00",
		"rebuildChildren" : "ThierryGoubier 3/12/2014 17:21:00",
		"rebuildContents" : "ThierryGoubier 3/12/2014 17:21:00",
		"sourceClass" : "ThierryGoubier 3/12/2014 17:21:00",
		"sourceCode" : "ThierryGoubier 3/12/2014 17:21:00",
		"styleClass" : "ThierryGoubier 3/12/2014 17:21:00",
		"title" : "ThierryGoubier 3/12/2014 17:21:00" } }
